soc_excel_convert/__init__.py
soc_excel_convert/__main__.py
soc_excel_convert/_internal/__init__.py
soc_excel_convert/_internal/result_code.py
soc_excel_convert/_internal/soc_excel_convert.py
soc_excel_convert/_utils/__init__.py
soc_excel_convert/_utils/excel_utils.py
soc_excel_convert/_utils/file_utils.py
soc_excel_convert/_utils/str_utils.py
soc_excel_convert-1.0.2.dist-info/LICENSE
soc_excel_convert-1.0.2.dist-info/METADATA
soc_excel_convert-1.0.2.dist-info/WHEEL
soc_excel_convert-1.0.2.dist-info/entry_points.txt
soc_excel_convert-1.0.2.dist-info/top_level.txt
soc_excel_convert-1.0.2.dist-info/RECORD
