Metadata-Version: 2.1
Name: soc-excel-convert
Version: 1.0.2
Summary: Convert Excel to markdown ....
Home-page: https://github.com/treeyh/soc-excel-convert
Author: Tree
Author-email: tree@ejyi.com
License: Apache License 2.0
Keywords: soc,excel,convert,markdown
Platform: UNKNOWN
Classifier: Programming Language :: Python :: 3
Classifier: License :: OSI Approved :: Apache Software License
Classifier: Operating System :: OS Independent
Requires-Python: >=3
Requires-Dist: et-xmlfile (>=1.0.1)
Requires-Dist: jdcal (>=1.4.1)
Requires-Dist: openpyxl (>=2.6.0)
Requires-Dist: pyperclip (>=1.8.1)
